LICENSE
MANIFEST.in
README.md
requirements.txt
setup.py
torch_model_state/__init__.py
torch_model_state/__main__.py
torch_model_state/__version__.py
torch_model_state/cli_main.py
torch_model_state/state_utils.py
torch_model_state.egg-info/PKG-INFO
torch_model_state.egg-info/SOURCES.txt
torch_model_state.egg-info/dependency_links.txt
torch_model_state.egg-info/entry_points.txt
torch_model_state.egg-info/requires.txt
torch_model_state.egg-info/top_level.txt
torch_model_state/configs/__init__.py
torch_model_state/configs/build/__init__.py
torch_model_state/configs/build/argument_config.py
torch_model_state/configs/build/state_file.py
torch_model_state/schema/argument_config.json
torch_model_state/schema/state_file.json