Metadata-Version: 2.1
Name: torch-model-state
Version: 0.0.8
Summary: PyTorch Model State Save & Load
Home-page: https://github.com/FebruaryBreeze/torch-model-state
Author: SF-Zhou
Author-email: sfzhou.scut@gmail.com
License: MIT
Keywords: PyTorch Model State
Platform: UNKNOWN
Requires-Python: >=3.6.0
